LICENSE
MANIFEST.in
README.md
requirements.txt
setup.cfg
setup.py
cryptory/__init__.py
cryptory/cryptory.py
cryptory.egg-info/PKG-INFO
cryptory.egg-info/SOURCES.txt
cryptory.egg-info/dependency_links.txt
cryptory.egg-info/requires.txt
cryptory.egg-info/top_level.txt
examples/example.py