Metadata-Version: 1.1
Name: cryptory
Version: 0.1.0
Summary: Retrieve historical cryptocurrency and other related data
Home-page: https://github.com/dashee87/cryptory
Author: David Sheehan
Author-email: davidfsheehan87@gamil.com
License: MIT
Keywords: cryptory cryptos data
Platform: UNKNOWN
Classifier: Development Status :: 3 - Alpha
Classifier: License :: OSI Approved :: MIT License
Classifier: Programming Language :: Python
Classifier: Programming Language :: Python :: 2.7
Classifier: Programming Language :: Python :: 3
Classifier: Operating System :: OS Independent
Classifier: Intended Audience :: Science/Research
Classifier: Intended Audience :: Developers
Classifier: Intended Audience :: Education
Classifier: Topic :: Scientific/Engineering :: Visualization
